stocksimpy/__init__.py
stocksimpy/addons/__init__.py
stocksimpy/addons/indicators.py
stocksimpy/addons/strategy.py
stocksimpy/core/__init__.py
stocksimpy/core/backtester.py
stocksimpy/core/portfolio.py
stocksimpy/core/stock_data.py
stocksimpy/utils/__init__.py
stocksimpy/utils/performance.py
stocksimpy/utils/visualize.py
stocksimpy-0.1.0.dist-info/licenses/LICENSE
stocksimpy-0.1.0.dist-info/METADATA
stocksimpy-0.1.0.dist-info/WHEEL
stocksimpy-0.1.0.dist-info/top_level.txt
stocksimpy-0.1.0.dist-info/RECORD
