Metadata-Version: 2.4
Name: stocksimpy
Version: 0.1.0
Summary: A beginner-friendly library for stock market data, backtesting, and strategies.
Author: Suleyman Sade
License: MIT License
Project-URL: Homepage, https://github.com/SuleymanSade/stocksimpy
Project-URL: Documentation, https://stocksimpy.readthedocs.io/
Project-URL: Source, https://github.com/SuleymanSade/stocksimpy
Project-URL: Issues, https://github.com/SuleymanSade/stocksimpy/issues
Requires-Python: >=3.10
License-File: LICENSE
Requires-Dist: pandas>=1.5
Requires-Dist: numpy>=1.21
Requires-Dist: yfinance>=0.2
Requires-Dist: matplotlib>=3.5
Provides-Extra: dev
Requires-Dist: black; extra == "dev"
Requires-Dist: isort; extra == "dev"
Requires-Dist: mypy; extra == "dev"
Requires-Dist: pytest; extra == "dev"
Requires-Dist: sphinx; extra == "dev"
Requires-Dist: sphinx-rtd-theme; extra == "dev"
Requires-Dist: pre-commit; extra == "dev"
Dynamic: license-file
